{
    "Ads": {
        "ShowAds": false,
        "ShowLoadingAds": false,
        "ClickCount": 1,
        "PriorityBanner": "admob",
        "priorityInterstitial": "admob",
        "PriorityNative": "admob",
        "PriorityReward": "admob",
        "IronAppKey": "85460dcd",
        "IronBanner": "DefaultBanner",
        "IronInterstitial": "DefaultInterstitial",
        "IronReward": "DefaultRewardedVideo",
        "MaxBanner": "29c514ae8f21ce41",
        "MaxInterstitial": "13d5de7a00d48501",
        "MaxNative": "53ae49d215c890c7",
        "MaxReward": "f70a8c6e8abddec5",
        "FanBanner": "xxxxx",
        "FanInterstitial": "xxxxx",
        "FanNative": "xxxxxx",
       "AdmobInterstitial":"ca-app-pub-3940256099942544/1033173712",
      "AdmobBanner":"ca-app-pub-3940256099942544/9214589741",
      "AdmobNative":"ca-app-pub-3940256099942544/2247696110",
      "AdmobReward":"ca-app-pub-3940256099942544/5224354917"
    },
    "ControlApp": {
        "ShowFootballScoresWarning": false,
        "ShowCricketSCoresWarning": false,
        "PlayerPackageName": "",
        "OnesignalID": "xxxxx",
        "ShowUpdate": false,
        "UpdateVersion": 2,
        "UpdateLink": ""
    }
}
